MANIFEST.in
readme.md
setup.py
hello/__init__.py
hello/hello.py
vasalskyy.egg-info/PKG-INFO
vasalskyy.egg-info/SOURCES.txt
vasalskyy.egg-info/dependency_links.txt
vasalskyy.egg-info/top_level.txt