Metadata-Version: 1.0
Name: vasalskyy
Version: 0.2.5
Summary: Hello world package
Home-page: UNKNOWN
Author: vasalskyy
Author-email: vasalskyyy@gmail.com
License: UNKNOWN
Platform: UNKNOWN
